favink/__init__.py
favink/fa.py
favink-2.0.0.dist-info/LICENSE
favink-2.0.0.dist-info/WHEEL
favink-2.0.0.dist-info/METADATA
favink-2.0.0.dist-info/RECORD
