Metadata-Version: 2.1
Name: favink
Version: 2.0.0
Summary: Over-simple Python finite automata (finite-state machine) implementation
Home-page: https://github.com/k-vinogradov/favink
License: MIT
Keywords: finite automata,finite state machine,state machine,vink
Author: Konstantin V.
Author-email: mail@k-vinogradov.ru
Requires-Python: >=3.5,<4.0
Classifier: License :: OSI Approved :: MIT License
Classifier: Programming Language :: Python :: 3
Classifier: Programming Language :: Python :: 3.5
Classifier: Programming Language :: Python :: 3.6
Classifier: Programming Language :: Python :: 3.7
Classifier: Programming Language :: Python :: 3.8
